devicesinlan/__init__.py
devicesinlan/data/devicesinlan.en.html
devicesinlan/data/devicesinlan.es.html
devicesinlan/data/devicesinlan.fr.html
devicesinlan/data/devicesinlan.ro.html
devicesinlan/data/devicesinlan.ru.html
devicesinlan/data/devicesinlan_gui.en.html
devicesinlan/data/devicesinlan_gui.es.html
devicesinlan/data/devicesinlan_gui.fr.html
devicesinlan/data/devicesinlan_gui.ro.html
devicesinlan/data/devicesinlan_gui.ru.html
devicesinlan/data/ieee-oui.txt
devicesinlan/devicesinlan.py
devicesinlan/i18n/devicesinlan_es.qm
devicesinlan/i18n/devicesinlan_es.ts
devicesinlan/i18n/devicesinlan_fr.qm
devicesinlan/i18n/devicesinlan_fr.ts
devicesinlan/i18n/devicesinlan_ro.qm
devicesinlan/i18n/devicesinlan_ro.ts
devicesinlan/i18n/devicesinlan_ru.qm
devicesinlan/i18n/devicesinlan_ru.ts
devicesinlan/images/add.png
devicesinlan/images/alarm_clock.png
devicesinlan/images/camera-photo.png
devicesinlan/images/camera-web.png
devicesinlan/images/cancel.png
devicesinlan/images/computer-laptop.png
devicesinlan/images/computer.png
devicesinlan/images/configure.png
devicesinlan/images/database.png
devicesinlan/images/devicesinlan.ico
devicesinlan/images/devicesinlan.png
devicesinlan/images/devicesinlan.qrc
devicesinlan/images/devicesinlan.xcf
devicesinlan/images/devicesinlan_doxygen.png
devicesinlan/images/devicesinlan_rc.py
devicesinlan/images/exit.png
devicesinlan/images/france.png
devicesinlan/images/help.png
devicesinlan/images/modem.png
devicesinlan/images/multimedia-player-apple-ipod.png
devicesinlan/images/multimedia-player.png
devicesinlan/images/open.png
devicesinlan/images/pda.png
devicesinlan/images/phone.png
devicesinlan/images/printer.png
devicesinlan/images/rumania.png
devicesinlan/images/rusia.png
devicesinlan/images/save.png
devicesinlan/images/scanner.png
devicesinlan/images/smartphone.png
devicesinlan/images/spain.png
devicesinlan/images/tablet.png
devicesinlan/images/uk.png
devicesinlan/images/update.png
devicesinlan/images/usb-wireless.png
devicesinlan-2.0.3.dist-info/METADATA
devicesinlan-2.0.3.dist-info/WHEEL
devicesinlan-2.0.3.dist-info/entry_points.txt
devicesinlan-2.0.3.dist-info/licenses/LICENSE.txt
devicesinlan-2.0.3.dist-info/RECORD
