Metadata-Version: 2.4
Name: devicesinlan
Version: 2.0.3
Summary: Find devices in a LAN and allows to make a list of known devices in order to detect not allowed ones
License-Expression: GPL-3.0-or-later
License-File: LICENSE.txt
Author: turulomio
Author-email: turulomio@yahoo.es
Requires-Python: >=3.10,<4
Classifier: Programming Language :: Python :: 3
Classifier: Programming Language :: Python :: 3.10
Classifier: Programming Language :: Python :: 3.11
Classifier: Programming Language :: Python :: 3.12
Classifier: Programming Language :: Python :: 3.13
Classifier: Programming Language :: Python :: 3.14
Requires-Dist: PyQt6 (>=6.10.1)
Requires-Dist: colorama (>=0.4.6)
Requires-Dist: pydicts (>=1.1.0)
Requires-Dist: scapy (>=2.7.0)
Requires-Dist: tqdm (>=4.67.1)
